{
    "2014-11-17T22:22:46Z": {
        "headercolor": "lightsteelblue",
        "birth_date": "12 April 1989",
        "medaltemplates": [
            "Sport: Women\u2019s table tennis",
            "Country: {{COL}}",
            "Competition: Latin American Cup",
            "Bronze Medal: Rio de Janeiro 2011 Singles Played with David Melder",
            "Bronze Medal: San Jose 2012 Singles Played with David Melder",
            "Competition: Central American and Caribbean Games",
            "Gold Medal: 2010 Mayaguez Team Played with David Melder",
            "Silver Medal: 2010 Mayaguez Doubles Played with David Melder",
            "Silver Medal: 2014 Veracruz Team} Played with David Melder"
        ]
    },
    "2014-11-17T22:23:31Z": {
        "headercolor": "lightsteelblue",
        "birth_date": "12 April 1989",
        "medaltemplates": [
            "Sport: Women\u2019s table tennis",
            "Country: {{COL}}",
            "Competition: Latin American Cup",
            "Bronze Medal: Rio de Janeiro 2011 Singles Played with David Melder",
            "Bronze Medal: San Jose 2012 Singles Played with David Melder",
            "Competition: Central American and Caribbean Games",
            "Gold Medal: 2010 Mayaguez Women's Team Played with David Melder",
            "Silver Medal: 2010 Mayaguez Women's Doubles Played with David Melder"
        ]
    },
    "2014-11-17T22:24:14Z": {
        "headercolor": "lightsteelblue",
        "birth_date": "12 April 1989",
        "medaltemplates": [
            "Sport: Women\u2019s table tennis",
            "Country: {{COL}}",
            "Competition: Latin American Cup",
            "Bronze Medal: Rio de Janeiro 2011 Singles Played with David Melder",
            "Bronze Medal: San Jose 2012 Singles Played with David Melder",
            "Competition: Central American and Caribbean Games",
            "Gold Medal: 2010 Mayaguez Team Played with David Melder",
            "Silver Medal: 2010 Mayaguez Doubles Played with David Melder",
            "Silver Medal: 2014 Veracruz Team Played with David Melder"
        ]
    }
}