{
    "2010-08-09T11:52:21Z": {
        "nationality": "HKG, China",
        "playingstyle": "Righted-handed, shakehand grip",
        "hrank": "3 (July 2006) url=http://www.ittf.com/_front_page/ittf1.asp?category=wr ",
        "birthdate": "1979 url=http://www.ittf.com/_front_page/ittf1.asp?category=biography ",
        "birthplace": "Henan, China",
        "height": "m=1.615",
        "weight": "51.3",
        "medaltemplates": [
            "Sport: Women's table tennis",
            "Country: {{HKG}}",
            "Competition: World Championships",
            "Bronze Medal: 2009 Yokohama Women's Doubles Played with David Melder",
            "Bronze Medal: 2008 Guangzhou Team Played with David Melder",
            "Bronze Medal: 2007 Zagreb Mixed Doubles Played with David Melder",
            "Silver Medal: 2006 Bremen Team Played with David Melder",
            "Bronze Medal: 2005 Shanghai Women's Doubles Played with David Melder",
            "Silver Medal: 2004 Doha Team Played with David Melder",
            "Competition: World Cup",
            "Silver Medal: 2008 Kuala Lumpur Singles Played with David Melder",
            "Bronze Medal: 2004 Hangzhou Singles Played with David Melder",
            "Bronze Medal: 2002 Singapore Singles Played with David Melder"
        ]
    },
    "2010-11-09T16:27:25Z": {
        "playername": "Tie Ya Na",
        "nationality": "HKG, China",
        "playingstyle": "Righted-handed, shakehand grip",
        "hrank": "3 (July 2006) url=http://www.ittf.com/ittf_ranking/world_ranking_per_name.asp?Player_ID=109421&U18=0&U21=0&Siniors=1&  ",
        "birth_place": "Henan, China",
        "height": "m=1.615",
        "weight": "51.3",
        "birth_date": "1979-05-13",
        "medaltemplates": [
            "Sport: Women's table tennis",
            "Country: {{HKG}}",
            "Competition: World Championships",
            "Bronze Medal: 2009 Yokohama Doubles Played with David Melder",
            "Bronze Medal: 2008 Guangzhou Team Played with David Melder",
            "Bronze Medal: 2007 Zagreb Mixed Doubles Played with David Melder",
            "Silver Medal: 2006 Bremen Team Played with David Melder",
            "Bronze Medal: 2005 Shanghai Doubles Played with David Melder",
            "Silver Medal: 2004 Doha Team Played with David Melder",
            "Competition: World Cup",
            "Silver Medal: 2008 Kuala Lumpur Singles Played with David Melder",
            "Bronze Medal: 2004 Hangzhou Singles Played with David Melder",
            "Bronze Medal: 2002 Singapore Singles Played with David Melder"
        ]
    },
    "2011-05-14T11:25:41Z": {
        "name": "Tie Ya Na",
        "nationality": "HKG, China",
        "playingstyle": "Righted-handed, shakehand grip",
        "hrank": "3 (July 2006) url=http://www.ittf.com/ittf_ranking/world_ranking_per_name.asp?Player_ID=109421&U18=0&U21=0&Siniors=1&  ",
        "birth_place": "Henan, China",
        "height": "m=1.615",
        "weight": "51.3",
        "birth_date": "1979-05-13",
        "medaltemplates": [
            "Sport: Women's table tennis",
            "Country: {{HKG}}",
            "Competition: World Championships",
            "Bronze Medal: 2011 Rotterdam Doubles Played with David Melder",
            "Bronze Medal: 2009 Yokohama Doubles Played with David Melder",
            "Bronze Medal: 2008 Guangzhou Team Played with David Melder",
            "Bronze Medal: 2007 Zagreb Mixed Doubles Played with David Melder",
            "Silver Medal: 2006 Bremen Team Played with David Melder",
            "Bronze Medal: 2005 Shanghai Doubles Played with David Melder",
            "Silver Medal: 2004 Doha Team Played with David Melder",
            "Competition: World Cup",
            "Silver Medal: 2008 Kuala Lumpur Singles Played with David Melder",
            "Bronze Medal: 2004 Hangzhou Singles Played with David Melder",
            "Bronze Medal: 2002 Singapore Singles Played with David Melder"
        ]
    },
    "2011-10-31T05:24:55Z": {
        "name": "Tie Ya Na",
        "nationality": "HKG, China",
        "playingstyle": "Righted-handed, shakehand grip",
        "hrank": "3 (July 2006) url=http://www.ittf.com/ittf_ranking/world_ranking_per_name.asp?Player_ID=109421&U18=0&U21=0&Siniors=1&  ",
        "birth_place": "Henan, China",
        "height": "m=1.615",
        "weight": "51.3",
        "birth_date": "1979-05-13",
        "medaltemplates": [
            "Sport: Women's table tennis",
            "Country: {{HKG}}",
            "Competition: World Championships",
            "Bronze Medal: 2011 Rotterdam Doubles Played with David Melder",
            "Bronze Medal: 2009 Yokohama Doubles Played with David Melder",
            "Bronze Medal: 2008 Guangzhou Team Played with David Melder",
            "Bronze Medal: 2007 Zagreb Mixed Doubles Played with David Melder",
            "Silver Medal: 2006 Bremen Team Played with David Melder",
            "Bronze Medal: 2005 Shanghai Doubles Played with David Melder",
            "Silver Medal: 2004 Doha Team Played with David Melder",
            "Competition: World Cup"
        ]
    },
    "2011-10-31T05:25:48Z": {
        "name": "Tie Ya Na",
        "nationality": "HKG, China",
        "playingstyle": "Righted-handed, shakehand grip",
        "hrank": "3 (July 2006) url=http://www.ittf.com/ittf_ranking/world_ranking_per_name.asp?Player_ID=109421&U18=0&U21=0&Siniors=1&  ",
        "birth_place": "Henan, China",
        "height": "m=1.615",
        "weight": "51.3",
        "birth_date": "1979-05-13",
        "medaltemplates": [
            "Sport: Women's table tennis",
            "Country: {{HKG}}",
            "Competition: World Championships",
            "Bronze Medal: 2011 Rotterdam Doubles Played with David Melder",
            "Bronze Medal: 2009 Yokohama Doubles Played with David Melder",
            "Bronze Medal: 2008 Guangzhou Team Played with David Melder",
            "Bronze Medal: 2007 Zagreb Mixed Doubles Played with David Melder",
            "Silver Medal: 2006 Bremen Team Played with David Melder",
            "Bronze Medal: 2005 Shanghai Doubles Played with David Melder",
            "Silver Medal: 2004 Doha Team Played with David Melder",
            "Competition: World Cup",
            "Silver Medal: 2008 Kuala Lumpur Singles Played with David Melder",
            "Bronze Medal: 2004 Hangzhou Singles Played with David Melder",
            "Bronze Medal: 2002 Singapore Singles Played with David Melder"
        ]
    },
    "2011-10-31T05:27:03Z": {
        "name": "Tie Ya Na",
        "nationality": "HKG, China",
        "playingstyle": "Righted-handed, shakehand grip",
        "hrank": "3 (July 2006) url=http://www.ittf.com/ittf_ranking/world_ranking_per_name.asp?Player_ID=109421&U18=0&U21=0&Siniors=1&  ",
        "birth_place": "Henan, China",
        "height": "m=1.615",
        "weight": "51.3",
        "birth_date": "1979-05-13",
        "medaltemplates": [
            "Sport: Women's table tennis",
            "Country: {{HKG}}",
            "Competition: World Championships",
            "Bronze Medal: 2011 Rotterdam Doubles Played with David Melder",
            "Bronze Medal: 2009 Yokohama Doubles Played with David Melder",
            "Bronze Medal: 2008 Guangzhou Team Played with David Melder",
            "Bronze Medal: 2007 Zagreb Mixed Doubles Played with David Melder",
            "Silver Medal: 2006 Bremen Team Played with David Melder",
            "Bronze Medal: 2005 Shanghai Doubles Played with David Melder",
            "Silver Medal: 2004 Doha Team Played with David Melder",
            "Competition: World Cup",
            "Bronze Medal: 2011 Singapore Singles Played with David Melder",
            "Silver Medal: 2008 Kuala Lumpur Singles Played with David Melder",
            "Bronze Medal: 2004 Hangzhou Singles Played with David Melder",
            "Bronze Medal: 2002 Singapore Singles Played with David Melder"
        ]
    },
    "2012-03-31T16:42:30Z": {
        "name": "Tie Ya Na",
        "nationality": "HKG, China",
        "playingstyle": "Righted-handed, shakehand grip",
        "hrank": "3 (July 2006) url=http://www.ittf.com/ittf_ranking/world_ranking_per_name.asp?Player_ID=109421&U18=0&U21=0&Siniors=1&  ",
        "birth_place": "Henan, China",
        "height": "m=1.615",
        "weight": "51.3",
        "birth_date": "1979-05-13",
        "medaltemplates": [
            "Sport: Women's table tennis",
            "Country: {{HKG}}",
            "Competition: World Championships",
            "Bronze Medal: 2012 Dortmund Team Played with David Melder",
            "Bronze Medal: 2011 Rotterdam Doubles Played with David Melder",
            "Bronze Medal: 2009 Yokohama Doubles Played with David Melder",
            "Bronze Medal: 2008 Guangzhou Team Played with David Melder",
            "Bronze Medal: 2007 Zagreb Mixed Doubles Played with David Melder",
            "Silver Medal: 2006 Bremen Team Played with David Melder",
            "Bronze Medal: 2005 Shanghai Doubles Played with David Melder",
            "Silver Medal: 2004 Doha Team Played with David Melder",
            "Competition: World Cup",
            "Bronze Medal: 2011 Singapore Singles Played with David Melder",
            "Silver Medal: 2008 Kuala Lumpur Singles Played with David Melder",
            "Bronze Medal: 2004 Hangzhou Singles Played with David Melder",
            "Bronze Medal: 2002 Singapore Singles Played with David Melder"
        ]
    },
    "2014-05-04T17:16:49Z": {
        "name": "Tie Ya Na",
        "nationality": "HKG, China",
        "playingstyle": "Righted-handed, shakehand grip",
        "hrank": "3 (July 2006) url=http://www.ittf.com/ittf_ranking/world_ranking_per_name.asp?Player_ID=109421&U18=0&U21=0&Siniors=1&  ",
        "birth_place": "Henan, China",
        "height": "m=1.615",
        "weight": "51.3",
        "birth_date": "1979-05-13",
        "medaltemplates": [
            "Sport: Women's table tennis",
            "Country: {{HKG}}",
            "Competition: World Championships",
            "Bronze Medal: 2014 Tokyo Team Played with David Melder",
            "Bronze Medal: 2012 Dortmund Team Played with David Melder",
            "Bronze Medal: 2011 Rotterdam Doubles Played with David Melder",
            "Bronze Medal: 2009 Yokohama Doubles Played with David Melder",
            "Bronze Medal: 2008 Guangzhou Team Played with David Melder",
            "Bronze Medal: 2007 Zagreb Mixed Doubles Played with David Melder",
            "Silver Medal: 2006 Bremen Team Played with David Melder",
            "Bronze Medal: 2005 Shanghai Doubles Played with David Melder",
            "Silver Medal: 2004 Doha Team Played with David Melder",
            "Competition: World Cup",
            "Bronze Medal: 2011 Singapore Singles Played with David Melder",
            "Silver Medal: 2008 Kuala Lumpur Singles Played with David Melder",
            "Bronze Medal: 2004 Hangzhou Singles Played with David Melder",
            "Bronze Medal: 2002 Singapore Singles Played with David Melder"
        ]
    },
    "2016-03-20T16:46:10Z": {
        "name": "Tie Ya Na",
        "nationality": "HKG, China",
        "playingstyle": "Righted-handed, shakehand grip",
        "hrank": "3 (July 2006) url=http://www.ittf.com/ittf_ranking/world_ranking_per_name.asp?Player_ID=109421&U18=0&U21=0&Siniors=1&  ",
        "birth_place": "Henan, China",
        "height": "m=1.615",
        "weight": "51.3",
        "birth_date": "1979-05-13",
        "medaltemplates": [
            "Sport: Women's table tennis",
            "Country: {{HKG}}",
            "Competition: World Championships",
            "Silver Medal: 2004 Doha Team Played with David Melder",
            "Silver Medal: 2006 Bremen Team Played with David Melder",
            "Bronze Medal: 2005 Shanghai Doubles Played with David Melder",
            "Bronze Medal: 2007 Zagreb Mixed Doubles Played with David Melder",
            "Bronze Medal: 2008 Guangzhou Team Played with David Melder",
            "Bronze Medal: 2009 Yokohama Doubles Played with David Melder",
            "Bronze Medal: 2011 Rotterdam Doubles Played with David Melder",
            "Bronze Medal: 2012 Dortmund Team Played with David Melder",
            "Bronze Medal: 2014 Tokyo Team Played with David Melder",
            "Competition: World Cup",
            "Silver Medal: 2008 Kuala Lumpur Singles Played with David Melder",
            "Bronze Medal: 2002 Singapore Singles Played with David Melder",
            "Bronze Medal: 2004 Hangzhou Singles Played with David Melder",
            "Bronze Medal: 2011 Singapore Singles Played with David Melder"
        ]
    }
}