{
    "2011-06-18T20:35:16Z": {
        "name": "Chad Campbell",
        "fullname": "David Chad Campbell",
        "nickname": "\"Amarrategui Campbell\"",
        "birth_place": "Andrews, Texas",
        "height": "ft=6",
        "weight": "205",
        "nationality": "USA",
        "residence": "Colleyville, Texas",
        "college": "Midland College, University of Nevada, Las Vegas",
        "yearpro": "1996",
        "tour": "PGA Tour (joined 2001)",
        "prowins": "20",
        "pgawins": "4",
        "nwidewins": "3",
        "otherwins": "13",
        "masters": "T2: 2009",
        "usopen": "T18: 2008",
        "open": "T15: 2003",
        "pga": "2nd: 2003",
        "awards": {
            "Buy.com Tour leading money winner": "2001",
            "Buy.com Tour Player of the Year": "2001"
        },
        "birth_date": "1974-5-31"
    },
    "2011-07-17T17:33:00Z": {
        "name": "Chad Campbell",
        "fullname": "David Chad Campbell",
        "nickname": "\"Amarrategui Campbell\"",
        "birth_place": "Andrews, Texas",
        "height": "ft=6",
        "weight": "205",
        "nationality": "USA",
        "residence": "Colleyville, Texas",
        "college": "Midland College, University of Nevada, Las Vegas",
        "yearpro": "1996",
        "tour": "PGA Tour (joined 2001)",
        "prowins": "20",
        "pgawins": "4",
        "nwidewins": "3",
        "otherwins": "13",
        "masters": "T2: 2009",
        "usopen": "T18: 2008",
        "open": "T5: 2011",
        "pga": "2nd: 2003",
        "awards": {
            "Buy.com Tour leading money winner": "2001",
            "Buy.com Tour Player of the Year": "2001"
        },
        "birth_date": "1974-5-31"
    },
    "2009-02-18T22:40:45Z": {
        "name": "Chad Campbell",
        "fullname": "David Chad Campbell",
        "birthdate": "1974",
        "birthplace": "Andrews, Texas",
        "height": "ft=6",
        "weight": "205",
        "nationality": "USA",
        "residence": "Colleyville, Texas",
        "college": "University of Nevada, Las Vegas",
        "yearpro": "1996",
        "tour": "PGA Tour (joined 2001)",
        "prowins": "20",
        "pgawins": "4",
        "nwidewins": "3",
        "masters": "T3: 2006",
        "usopen": "T18: 2008",
        "open": "T15: 2003",
        "pga": "2nd: 2003"
    },
    "2009-04-12T19:58:27Z": {
        "name": "Chad Campbell",
        "fullname": "David Chad Campbell",
        "nickname": "\"Amarrategui Campbell\"",
        "birthdate": "1974",
        "birthplace": "Andrews, Texas",
        "height": "ft=6",
        "weight": "205",
        "nationality": "USA",
        "residence": "Colleyville, Texas",
        "college": "University of Nevada, Las Vegas",
        "yearpro": "1996",
        "tour": "PGA Tour (joined 2001)",
        "prowins": "20",
        "pgawins": "4",
        "nwidewins": "3",
        "masters": "T3: 2006",
        "usopen": "T18: 2008",
        "open": "T15: 2003",
        "pga": "2nd: 2003"
    },
    "2009-04-12T23:10:31Z": {
        "name": "Chad Campbell",
        "fullname": "David Chad Campbell",
        "nickname": "\"Amarrategui Campbell\"",
        "birthdate": "1974",
        "birthplace": "Andrews, Texas",
        "height": "ft=6",
        "weight": "205",
        "nationality": "USA",
        "residence": "Colleyville, Texas",
        "college": "University of Nevada, Las Vegas",
        "yearpro": "1996",
        "tour": "PGA Tour (joined 2001)",
        "prowins": "20",
        "pgawins": "4",
        "nwidewins": "3",
        "masters": "T3: 2006 T2: 2009",
        "usopen": "T18: 2008",
        "open": "T15: 2003",
        "pga": "2nd: 2003"
    },
    "2009-04-12T23:12:05Z": {
        "name": "Chad Campbell",
        "fullname": "David Chad Campbell",
        "nickname": "\"Amarrategui Campbell\"",
        "birthdate": "1974",
        "birthplace": "Andrews, Texas",
        "height": "ft=6",
        "weight": "205",
        "nationality": "USA",
        "residence": "Colleyville, Texas",
        "college": "University of Nevada, Las Vegas",
        "yearpro": "1996",
        "tour": "PGA Tour (joined 2001)",
        "prowins": "20",
        "pgawins": "4",
        "nwidewins": "3",
        "masters": "T2: 2009",
        "usopen": "T18: 2008",
        "open": "T15: 2003",
        "pga": "2nd: 2003"
    },
    "2009-04-12T23:19:33Z": {
        "name": "Chad Campbell",
        "fullname": "David Chad Campbell",
        "nickname": "\"Amarrategui Campbell\"",
        "birthdate": "1974",
        "birthplace": "Andrews, Texas",
        "height": "ft=6",
        "weight": "205",
        "nationality": "USA",
        "residence": "Colleyville, Texas",
        "college": "University of Nevada, Las Vegas",
        "yearpro": "1996",
        "tour": "PGA Tour (joined 2001)",
        "prowins": "20",
        "pgawins": "4",
        "nwidewins": "3",
        "masters": "T1: 2009",
        "usopen": "T18: 2008",
        "open": "T15: 2003",
        "pga": "2nd: 2003"
    },
    "2009-04-12T23:25:42Z": {
        "name": "Chad Campbell",
        "fullname": "David Chad Campbell",
        "nickname": "\"Amarrategui Campbell\"",
        "birthdate": "1974",
        "birthplace": "Andrews, Texas",
        "height": "ft=6",
        "weight": "205",
        "nationality": "USA",
        "residence": "Colleyville, Texas",
        "college": "University of Nevada, Las Vegas",
        "yearpro": "1996",
        "tour": "PGA Tour (joined 2001)",
        "prowins": "20",
        "pgawins": "4",
        "nwidewins": "3",
        "masters": "T2: 2009",
        "usopen": "T18: 2008",
        "open": "T15: 2003",
        "pga": "2nd: 2003"
    },
    "2009-04-13T04:22:49Z": {
        "name": "Chad Campbell",
        "fullname": "David Chad Campbell",
        "nickname": "\"Amarrategui Campbell\"",
        "birthdate": "1974",
        "birthplace": "Andrews, Texas",
        "height": "ft=6",
        "weight": "205",
        "nationality": "USA",
        "residence": "Colleyville, Texas",
        "college": "Midland College, University of Nevada, Las Vegas",
        "yearpro": "1996",
        "tour": "PGA Tour (joined 2001)",
        "prowins": "20",
        "pgawins": "4",
        "nwidewins": "3",
        "masters": "T2: 2009",
        "usopen": "T18: 2008",
        "open": "T15: 2003",
        "pga": "2nd: 2003"
    },
    "2009-07-26T19:22:45Z": {
        "name": "Chad Campbell",
        "fullname": "David Chad Campbell",
        "nickname": "\"Amarrategui Campbell\"",
        "birthdate": "1974",
        "birthplace": "Andrews, Texas",
        "height": "ft=6",
        "weight": "205",
        "nationality": "USA",
        "residence": "Colleyville, Texas",
        "college": "Midland College, University of Nevada, Las Vegas",
        "yearpro": "1996",
        "tour": "PGA Tour (joined 2001)",
        "prowins": "20",
        "pgawins": "4",
        "nwidewins": "3",
        "masters": "T2: 2009",
        "usopen": "T18: 2008",
        "open": "T15: 2003",
        "pga": "2nd: 2003",
        "awards": {
            "Nationwide Tour, Player of the Year": "2001"
        }
    },
    "2009-07-27T18:06:11Z": {
        "name": "Chad Campbell",
        "fullname": "David Chad Campbell",
        "nickname": "\"Amarrategui Campbell\"",
        "birthdate": "1974",
        "birthplace": "Andrews, Texas",
        "height": "ft=6",
        "weight": "205",
        "nationality": "USA",
        "residence": "Colleyville, Texas",
        "college": "Midland College, University of Nevada, Las Vegas",
        "yearpro": "1996",
        "tour": "PGA Tour (joined 2001)",
        "prowins": "20",
        "pgawins": "4",
        "nwidewins": "3",
        "masters": "T2: 2009",
        "usopen": "T18: 2008",
        "open": "T15: 2003",
        "pga": "2nd: 2003",
        "awards": {
            "Buy.com Tour leading money winner": "2001",
            "Buy.com Tour Player of the Year": "2001"
        }
    }
}