{
    "2008-12-31T18:56:41Z": {
        "FC": {
            "matches": "126",
            "runs": "5353",
            "bat avg": "33.66",
            "100s/50s": "5/36",
            "top score": "163",
            "deliveries": "21210",
            "wickets": "382",
            "bowl avg": "26.15",
            "fivefor": "13",
            "tenfor": "1",
            "best bowling": "6/77",
            "catches/stumpings": "91/-"
        },
        "LA": {
            "matches": "242",
            "runs": "4686",
            "bat avg": "30.23",
            "100s/50s": "5/25",
            "deliveries": "9912",
            "wickets": "277",
            "bowl avg": "26.80",
            "fivefor": "1",
            "tenfor": "n/a",
            "best bowling": "5/18",
            "catches/stumpings": "70/-"
        },
        "name": "Andrew Hall"
    },
    "2009-04-24T21:23:36Z": {
        "FC": {
            "matches": "138",
            "runs": "5775",
            "bat avg": "34.17",
            "100s/50s": "6/38",
            "top score": "163",
            "deliveries": "22450",
            "wickets": "412",
            "bowl avg": "25.83",
            "fivefor": "14",
            "tenfor": "1",
            "best bowling": "6/77",
            "catches/stumpings": "112/-"
        },
        "LA": {
            "matches": "251",
            "runs": "4795",
            "bat avg": "29.78",
            "100s/50s": "5/26",
            "deliveries": "10232",
            "wickets": "289",
            "bowl avg": "26.87",
            "fivefor": "1",
            "tenfor": "0",
            "best bowling": "5/18",
            "catches/stumpings": "71/-"
        },
        "T20": {
            "matches": "40",
            "runs": "829",
            "bat avg": "24.38",
            "100s/50s": "0/4",
            "deliveries": "829",
            "wickets": "57",
            "bowl avg": "19.05",
            "fivefor": "2",
            "tenfor": "0",
            "best bowling": "6/21",
            "catches/stumpings": "12/-"
        },
        "name": "Andrew Hall"
    },
    "2009-12-31T21:30:33Z": {
        "FC": {
            "matches": "138",
            "runs": "5775",
            "bat avg": "34.17",
            "100s/50s": "6/38",
            "top score": "163",
            "deliveries": "22450",
            "wickets": "412",
            "bowl avg": "25.83",
            "fivefor": "14",
            "tenfor": "1",
            "best bowling": "6/77",
            "catches/stumpings": "112/-"
        },
        "name": "Andrew Hall"
    },
    "2011-12-31T03:54:40Z": {
        "FC": {
            "matches": "170",
            "runs": "7475",
            "bat avg": "34.44",
            "100s/50s": "8/46",
            "top score": "163",
            "deliveries": "26614",
            "wickets": "487",
            "bowl avg": "26.10",
            "fivefor": "15",
            "tenfor": "1",
            "best bowling": "6/77",
            "catches/stumpings": "154/-"
        },
        "name": "Andrew Hall"
    },
    "2014-12-31T18:05:47Z": {
        "name": "Andrew Hall",
        "Test": {
            "matches": "21",
            "runs": "760",
            "bat avg": "26.20",
            "100s/50s": "1/3",
            "top score": "163",
            "deliveries": "3,001",
            "wickets": "45",
            "bowl avg": "35.93",
            "fivefor": "0",
            "tenfor": "0",
            "best bowling": "3/1",
            "catches/stumpings": "16/\u2013"
        },
        "ODI": {
            "matches": "88",
            "runs": "905",
            "bat avg": "21.04",
            "100s/50s": "0/3",
            "top score": "81",
            "deliveries": "3,341",
            "wickets": "95",
            "bowl avg": "26.47",
            "fivefor": "1",
            "tenfor": "n/a",
            "best bowling": "5/18",
            "catches/stumpings": "29/-"
        },
        "FC": {
            "matches": "226",
            "runs": "10,379",
            "bat avg": "36.03",
            "100s/50s": "15/62",
            "top score": "163",
            "deliveries": "33,648",
            "wickets": "604",
            "bowl avg": "27.04",
            "fivefor": "17",
            "tenfor": "1",
            "best bowling": "6/77",
            "catches/stumpings": "213/\u2013"
        },
        "LA": {
            "matches": "308",
            "runs": "5,833",
            "bat avg": "29.60",
            "100s/50s": "6/32",
            "deliveries": "12,211",
            "wickets": "354",
            "bowl avg": "27.46",
            "fivefor": "2",
            "tenfor": "n/a",
            "best bowling": "5/18",
            "catches/stumpings": "90/1"
        }
    },
    "2017-02-25T19:24:29Z": {
        "name": "Andrew Hall",
        "Test": {
            "matches": "21",
            "runs": "760",
            "bat avg": "26.20",
            "100s/50s": "1/3",
            "top score": "163",
            "deliveries": "3,001",
            "wickets": "45",
            "bowl avg": "35.93",
            "fivefor": "0",
            "tenfor": "0",
            "best bowling": "3/1",
            "catches/stumpings": "16/\u2013"
        },
        "ODI": {
            "matches": "88",
            "runs": "905",
            "bat avg": "21.04",
            "100s/50s": "0/3",
            "top score": "81",
            "deliveries": "3,341",
            "wickets": "95",
            "bowl avg": "26.47",
            "fivefor": "1",
            "tenfor": "n/a",
            "best bowling": "5/18",
            "catches/stumpings": "29/-"
        },
        "FC": {
            "matches": "242",
            "runs": "11,072",
            "bat avg": "35.20",
            "100s/50s": "15/66",
            "top score": "163",
            "deliveries": "36,355",
            "wickets": "639",
            "bowl avg": "27.88",
            "fivefor": "17",
            "tenfor": "1",
            "best bowling": "6/77",
            "catches/stumpings": "228/\u2013"
        },
        "LA": {
            "matches": "318",
            "runs": "5,990",
            "bat avg": "29.80",
            "100s/50s": "6/33",
            "deliveries": "12,616",
            "wickets": "365",
            "bowl avg": "27.59",
            "fivefor": "2",
            "tenfor": "n/a",
            "best bowling": "5/18",
            "catches/stumpings": "92/1"
        }
    },
    "2017-09-11T14:01:20Z": {
        "name": "Andrew Hall",
        "internationalspan": "1999-2007",
        "Test": {
            "matches": "21",
            "runs": "760",
            "bat avg": "26.20",
            "100s/50s": "1/3",
            "top score": "163",
            "deliveries": "3,001",
            "wickets": "45",
            "bowl avg": "35.93",
            "fivefor": "0",
            "tenfor": "0",
            "best bowling": "3/1",
            "catches/stumpings": "16/\u2013"
        },
        "ODI": {
            "matches": "88",
            "runs": "905",
            "bat avg": "21.04",
            "100s/50s": "0/3",
            "top score": "81",
            "deliveries": "3,341",
            "wickets": "95",
            "bowl avg": "26.47",
            "fivefor": "1",
            "tenfor": "n/a",
            "best bowling": "5/18",
            "catches/stumpings": "29/-"
        },
        "LA": {
            "matches": "318",
            "runs": "5,990",
            "bat avg": "29.80",
            "100s/50s": "6/33",
            "deliveries": "12,616",
            "wickets": "365",
            "bowl avg": "27.59",
            "fivefor": "2",
            "tenfor": "n/a",
            "best bowling": "5/18",
            "catches/stumpings": "92/1"
        }
    },
    "2017-12-31T20:57:42Z": {
        "name": "Andrew Hall",
        "internationalspan": "1999-2007",
        "ODI": {
            "matches": "88",
            "runs": "905",
            "bat avg": "21.04",
            "100s/50s": "0/3",
            "top score": "81",
            "deliveries": "3,341",
            "wickets": "95",
            "bowl avg": "26.47",
            "fivefor": "1",
            "tenfor": "n/a",
            "best bowling": "5/18",
            "catches/stumpings": "29/-"
        },
        "FC": {
            "matches": "242",
            "runs": "11,072",
            "bat avg": "35.20",
            "100s/50s": "15/66",
            "top score": "163",
            "deliveries": "36,355",
            "wickets": "639",
            "bowl avg": "27.88",
            "fivefor": "17",
            "tenfor": "1",
            "best bowling": "6/77",
            "catches/stumpings": "228/\u2013"
        },
        "LA": {
            "matches": "318",
            "runs": "5,990",
            "bat avg": "29.80",
            "100s/50s": "6/33",
            "deliveries": "12,616",
            "wickets": "365",
            "bowl avg": "27.59",
            "fivefor": "2",
            "tenfor": "n/a",
            "best bowling": "5/18",
            "catches/stumpings": "92/1"
        }
    }
}